lambdabuild/__init__.py
lambdabuild/byteequivalentzip.py
lambdabuild/clean_lambda_directory_before_zip_python2.py
lambdabuild/clean_lambda_directory_before_zip_python3.py
lambdabuild/cli.py
lambdabuild/collectsources.py
lambdabuild/dockerfiletemplates.py
lambdabuild/dockerwrapper.py
lambdabuild/runtimeinfo.py
lambdabuild/untar.py
lambdabuild-0.2.5.dist-info/LICENSE
lambdabuild-0.2.5.dist-info/METADATA
lambdabuild-0.2.5.dist-info/WHEEL
lambdabuild-0.2.5.dist-info/entry_points.txt
lambdabuild-0.2.5.dist-info/top_level.txt
lambdabuild-0.2.5.dist-info/RECORD
