Metadata-Version: 2.1
Name: lambdabuild
Version: 0.2.5
Summary: Easily build AWS lambda artifacts and layers, correctly
Home-page: https://github.com/shlomimatichin/lambdabuild
Author: Shlomi Matichin
Author-email: shlomomatichin@gmail.com
License: UNKNOWN
Keywords: AWS,lambda,build,docker
Platform: UNKNOWN
Classifier: Programming Language :: Python :: 3
Classifier: License :: OSI Approved :: MIT License
Classifier: Operating System :: OS Independent
Classifier: Environment :: Console
Classifier: Intended Audience :: Developers
